khmerml/__init__.py
khmerml/machine_learning.py
khmerml/setup.py
khmerml/algorithms/__init__.py
khmerml/algorithms/base.py
khmerml/algorithms/bayes/__init__.py
khmerml/algorithms/bayes/bayes_base.py
khmerml/algorithms/bayes/naive_bayes.py
khmerml/algorithms/decisiontree/__init__.py
khmerml/algorithms/decisiontree/decision_tree.py
khmerml/algorithms/decisiontree/tree.py
khmerml/algorithms/neural_network/__init__.py
khmerml/algorithms/neural_network/neural_network.py
khmerml/algorithms/neural_network/neural_network_base.py
khmerml/preprocessing/__init__.py
khmerml/preprocessing/preprocessing_data.py
khmerml/preprocessing/read_content.py
khmerml/utils/__init__.py
khmerml/utils/bg_colors.py
khmerml/utils/file_util.py
khmerml/utils/khmersegment.py
khmerml/utils/log.py
khmerml/utils/unicodesplit.py
khmerml-0.0.12.dist-info/DESCRIPTION.rst
khmerml-0.0.12.dist-info/METADATA
khmerml-0.0.12.dist-info/RECORD
khmerml-0.0.12.dist-info/WHEEL
khmerml-0.0.12.dist-info/metadata.json
khmerml-0.0.12.dist-info/top_level.txt
